Learning/fadder.v
/* Full Adder implementation

S= A⊕B⊕Cin
Cout=(A&B||Cin(A⊕B))

*/
//Data Flow
module FA_df(S,C_out,A,B,C_in);

    input A,B,C_in;
    output S,C_out;

    assign S = A ^ B ^ C_in;
    assign C_out = ( A & B ) | ( C_in & ( A ^ B ));

endmodule

//Behavioral Level
/*
module FA_bl(S,C_out,A,B,C_in);

    input A,B,C_in;
    output reg S,C_out;

    always @(*)begin
        S = A ^ B ^ C_in;
        C_out = ( A & B ) | ( C_in & ( A ^ B ));
    end

endmodule
*/

//Gate level Modeling
/*
module FA_gl(S,C_out,A,B,C_in);

    input A,B,C_in;
    output S,C_out;

    //literal wire, think of them as temp values or "holding spaces"
    wire S1,C1,C2;

    //Sum
    xor u1(S1,A,B);
    xor u2(S,S1,C_in);

    //Carry
    and u3(C1,A,B);
    and u4(C2,S1,C_in);
    or u5 (C_out,C1,C2);

endmodule
    */

Learning/fadderTB.v
`timescale 1ns/1ns
`include "fadder.v"

module hadderTB;

//variables (basically inputs reg, outputs wire)
    reg A,B,C_in;
    wire S,C_out;

    //uut is just a name, you can call it whatever. uut means unit under test.
    FA_df uut(S,C_out,A,B,C_in);

    initial begin
        //creates vcd file
        $dumpfile("fadderTB.vcd");
        $dumpvars(0, hadderTB);
        //debug display and formating
        $display("Time\tA B Cin| S Cout");
        $monitor("%g\t%b %b %b | %b %b", $time, A,B,C_in,S,C_out);

        //Test cases (#10 is a 10ns delay)
        A=0;B=0;C_in=0;#10;
        A=1;B=0;C_in=0;#10;
        A=0;B=1;C_in=0;#10;
        A=1;B=1;C_in=0;#10;
        A=0;B=0;C_in=1;#10;
        A=1;B=0;C_in=1;#10;
        A=0;B=1;C_in=1;#10;
        A=1;B=1;C_in=1;#10;


    end



endmodule

Learning/fadderTB.vcd
$date
	Thu Jul 23 14:15:06 2026
$end
$version
	Icarus Verilog
$end
$timescale
	1ns
$end
$scope module hadderTB $end
$var wire 1 ! S $end
$var wire 1 " C_out $end
$var reg 1 # A $end
$var reg 1 $ B $end
$var reg 1 % C_in $end
$scope module uut $end
$var wire 1 # A $end
$var wire 1 $ B $end
$var wire 1 % C_in $end
$var wire 1 " C_out $end
$var wire 1 ! S $end
$upscope $end
$upscope $end
$enddefinitions $end
$comment Show the parameter values. $end
$dumpall
$end
#0
$dumpvars
0%
0$
0#
0"
0!
$end
#10
1!
1#
#20
1$
0#
#30
0!
1"
1#
#40
0"
1!
1%
0$
0#
#50
1"
0!
1#
#60
1$
0#
#70
1!
1#
